crypter/__init__.py
crypter/crypter.py
authcrypter-1.0.dist-info/METADATA
authcrypter-1.0.dist-info/WHEEL
authcrypter-1.0.dist-info/top_level.txt
authcrypter-1.0.dist-info/RECORD
