Metadata-Version: 2.1
Name: authcrypter
Version: 1.0
Summary: Encryption tools wrapper library
Home-page: https://source.app.pconnect.biz/projects/RBD/repos/crypter/browse
Author: Alexander Filimonov
Author-email: alexander.filimonov@pmi.com
License: PMSM
Platform: UNKNOWN
Requires-Dist: pycrypto
